deepstack_sdk/__init__.py
deepstack_sdk/base.py
deepstack_sdk/config.py
deepstack_sdk/detection.py
deepstack_sdk/face.py
deepstack_sdk/scene.py
deepstack_sdk/structs.py
deepstack_sdk/utils.py
deepstack_sdk/viz.py
deepstack_sdk-0.2.1.dist-info/LICENSE
deepstack_sdk-0.2.1.dist-info/METADATA
deepstack_sdk-0.2.1.dist-info/WHEEL
deepstack_sdk-0.2.1.dist-info/top_level.txt
deepstack_sdk-0.2.1.dist-info/RECORD
