Metadata-Version: 2.1
Name: deepstack-sdk
Version: 0.2.1
Summary: DeepStack Python SDK
Home-page: https://github.com/johnolafenwa/DeepStackPython
Author: John Olafenwa and Moses Olafenwa
Author-email: UNKNOWN
License: MIT
Platform: UNKNOWN
Classifier: Programming Language :: Python :: 3
Classifier: License :: OSI Approved :: MIT License
Classifier: Operating System :: OS Independent
Requires-Dist: pillow
Requires-Dist: opencv-python
Requires-Dist: matplotlib
Requires-Dist: requests
Requires-Dist: pytest
Requires-Dist: validators
